odoo/addons/model_read_only/README.rst
odoo/addons/model_read_only/__init__.py
odoo/addons/model_read_only/__manifest__.py
odoo/addons/model_read_only/i18n/it.po
odoo/addons/model_read_only/i18n/model_read_only.pot
odoo/addons/model_read_only/migrations/14.0.2.0.0/post-migration.py
odoo/addons/model_read_only/migrations/14.0.2.0.0/pre-migration.py
odoo/addons/model_read_only/models/__init__.py
odoo/addons/model_read_only/models/models.py
odoo/addons/model_read_only/readme/CONTRIBUTORS.rst
odoo/addons/model_read_only/readme/DESCRIPTION.rst
odoo/addons/model_read_only/readme/USAGE.rst
odoo/addons/model_read_only/security/ir.model.access.csv
odoo/addons/model_read_only/static/description/icon.png
odoo/addons/model_read_only/static/description/index.html
odoo/addons/model_read_only/tests/__init__.py
odoo/addons/model_read_only/tests/test_models.py
odoo/addons/model_read_only/views/views.xml
odoo14_addon_model_read_only-14.0.3.0.2.dist-info/METADATA
odoo14_addon_model_read_only-14.0.3.0.2.dist-info/WHEEL
odoo14_addon_model_read_only-14.0.3.0.2.dist-info/top_level.txt
odoo14_addon_model_read_only-14.0.3.0.2.dist-info/RECORD
